json_schema_utils-0.8.6.dist-info/licenses/LICENSE
jsutils/__init__.py
jsutils/convert.py
jsutils/inline.py
jsutils/recurse.py
jsutils/schemas.py
jsutils/scripts.py
jsutils/simplify.py
jsutils/stats.py
jsutils/utils.py
json_schema_utils-0.8.6.dist-info/METADATA
json_schema_utils-0.8.6.dist-info/WHEEL
json_schema_utils-0.8.6.dist-info/entry_points.txt
json_schema_utils-0.8.6.dist-info/top_level.txt
json_schema_utils-0.8.6.dist-info/RECORD
