Metadata-Version: 2.4
Name: json_schema_utils
Version: 0.8.6
Summary: JSON Schema Utils
Author: Fabien Coelho, Claire Yannou-Medrala
License-Expression: CC0-1.0
Project-URL: repository, https://github.com/zx80/json-schema-utils
Classifier: Topic :: Software Development
Requires-Python: >=3.12
License-File: LICENSE
Requires-Dist: requests
Requires-Dist: jschon
Requires-Dist: jsonschema[format]
Provides-Extra: dev
Requires-Dist: ruff; extra == "dev"
Requires-Dist: flake8; extra == "dev"
Requires-Dist: pyright; extra == "dev"
Provides-Extra: dist
Requires-Dist: build; extra == "dist"
Requires-Dist: twine; extra == "dist"
Requires-Dist: wheel; extra == "dist"
Dynamic: license-file
